expanse/__init__.py
expanse/__version__.py
expanse/assets/config/app.py
expanse/assets/config/cors.py
expanse/assets/config/database.py
expanse/assets/config/encryption.py
expanse/assets/config/http.py
expanse/assets/config/paths.py
expanse/assets/config/schematic.py
expanse/assets/config/session.py
expanse/assets/config/static.py
expanse/assets/config/view.py
expanse/configuration/__init__.py
expanse/configuration/config.py
expanse/console/__init__.py
expanse/console/command_loader.py
expanse/console/commands/__init__.py
expanse/console/commands/command.py
expanse/console/commands/help.py
expanse/console/commands/list.py
expanse/console/console.py
expanse/container/__init__.py
expanse/container/container.py
expanse/container/exceptions.py
expanse/contracts/__init__.py
expanse/contracts/debug/__init__.py
expanse/contracts/debug/exception_handler.py
expanse/contracts/debug/exception_renderer.py
expanse/contracts/encryption/__init__.py
expanse/contracts/encryption/encryptor.py
expanse/contracts/routing/__init__.py
expanse/contracts/routing/registrar.py
expanse/contracts/routing/route_collection.py
expanse/contracts/routing/router.py
expanse/core/__init__.py
expanse/core/application.py
expanse/core/application_builder.py
expanse/core/bootstrap/__init__.py
expanse/core/bootstrap/boot_providers.py
expanse/core/bootstrap/bootstrapper.py
expanse/core/bootstrap/load_configuration.py
expanse/core/bootstrap/load_environment_variables.py
expanse/core/bootstrap/register_providers.py
expanse/core/console/__init__.py
expanse/core/console/commands/__init__.py
expanse/core/console/commands/make/__init__.py
expanse/core/console/commands/make/controller.py
expanse/core/console/commands/make/middleware.py
expanse/core/console/commands/routes/__init__.py
expanse/core/console/commands/routes/list.py
expanse/core/console/commands/serve.py
expanse/core/console/portal.py
expanse/core/console/providers/__init__.py
expanse/core/console/providers/command_service_provider.py
expanse-0.6.0.dist-info/WHEEL
expanse-0.6.0.dist-info/METADATA
expanse-0.6.0.dist-info/RECORD
