Metadata-Version: 2.4
Name: expanse
Version: 0.6.0
Summary: The limitless Python web framework
Keywords: expanse,framework
Author: Sébastien Eustace
Author-email: Sébastien Eustace <sebastien@eustace.io>
License-Expression: MIT
Requires-Dist: alembic>=1.13.2
Requires-Dist: anyio>=4.2.0
Requires-Dist: baize>=0.22.0
Requires-Dist: cleo>=2.1.0
Requires-Dist: cryptography>=44.0.0
Requires-Dist: filelock>=3.16.1
Requires-Dist: httpx>=0.26.0
Requires-Dist: inflection>=0.5.1
Requires-Dist: jinja2>=3.1.6
Requires-Dist: pendulum[test]>=3.1.0
Requires-Dist: pydantic>=2.11.3
Requires-Dist: pydantic-settings>=2.8.1
Requires-Dist: pygments>=2.18.0
Requires-Dist: sqlalchemy[asyncio]>=2.0.25
Requires-Dist: uvicorn[standard]>=0.23.2
Requires-Dist: msgspec>=0.19.0
Requires-Python: >=3.12
Project-URL: Homepage, https://expanse-framework.com/
Project-URL: Repository, https://github.com/expanse-framework/expanse
Project-URL: Documentation, https://expanse-framework.com/docs
